nbautoeval/TAGS
nbautoeval/__init__.py
nbautoeval/area.py.dup
nbautoeval/args.py
nbautoeval/callrenderer.py
nbautoeval/content.py
nbautoeval/dummy-html.ipynb
nbautoeval/exercise_class.py
nbautoeval/exercise_function.py
nbautoeval/exercise_generator.py
nbautoeval/exercise_regexp.py
nbautoeval/helpers.py
nbautoeval/nohup.out
nbautoeval/quiz.py
nbautoeval/quiz_help.py
nbautoeval/quiz_loader.py
nbautoeval/renderer.py
nbautoeval/storage.py
nbautoeval/tooltip.html
nbautoeval/version.py
nbautoeval/.ipynb_checkpoints/dummy-html-checkpoint.ipynb
nbautoeval/.macnb/log
nbautoeval/.macnb/pid
nbautoeval/.macnb/port
nbautoeval/.macnb/token
nbautoeval/grading/__init__.py
nbautoeval/grading/quiz_scan.py
nbautoeval-1.8.0.dist-info/METADATA
nbautoeval-1.8.0.dist-info/WHEEL
nbautoeval-1.8.0.dist-info/entry_points.txt
nbautoeval-1.8.0.dist-info/licenses/LICENSE
nbautoeval-1.8.0.dist-info/RECORD
