Metadata-Version: 2.3
Name: nbautoeval
Version: 1.8.0
Summary: A mini framework to implement auto-evaluated exercises in Jupyter notebooks
Project-URL: Homepage, https://github.com/parmentelat/nbautoeval
Author-email: Thierry Parmentelat <thierry.parmentelat@inria.fr>
License: CC-BY-SA-4.0
Keywords: Jupyter,auto-evaluation,exercises
Requires-Python: >=3.10
Requires-Dist: ipython
Requires-Dist: ipywidgets
Requires-Dist: myst-parser
Requires-Dist: numpy
Requires-Dist: pyyaml
